roolang/__init__.py
roolang/roolexer.py
roolang/rooparser.py
tests/__init__.py
tests/__main__.py
roolang-0.0.2a0.dist-info/LICENSE
roolang-0.0.2a0.dist-info/METADATA
roolang-0.0.2a0.dist-info/WHEEL
roolang-0.0.2a0.dist-info/top_level.txt
roolang-0.0.2a0.dist-info/RECORD
